mavsec/__init__.py
mavsec/_info.py
mavsec/general.py
mavsec/project.py
mavsec/properties.py
mavsec/py.typed
mavsec/schema.py
mavsec/_gui/__init__.py
mavsec/_gui/menus.py
mavsec/_gui/proj_tabs.py
mavsec-1.0.0.dist-info/LICENSE
mavsec-1.0.0.dist-info/METADATA
mavsec-1.0.0.dist-info/WHEEL
mavsec-1.0.0.dist-info/entry_points.txt
mavsec-1.0.0.dist-info/top_level.txt
mavsec-1.0.0.dist-info/RECORD
