Metadata-Version: 2.1
Name: mavsec
Version: 1.0.0
Summary: A tool for the creation of JasperGold SVP principle tcl files.
Author-email: Benjamin Davis <allrisc.dev@gmail.com>
License: GNU GENERAL PUBLIC LICENSE
Project-URL: Homepage, https://github.com/RISCY-Lib/mavsec
Project-URL: Documentation, https://github.com/RISCY-Lib/mavsec/blob/main/README.md
Keywords: Verilog,tool,SystemVerilog,JasperGold,SVP,Security,Verification,Formal,Property,Assertion
Classifier: Development Status :: 3 - Alpha
Classifier: License :: OSI Approved :: GNU General Public License v3 or later (GPLv3+)
Classifier: Programming Language :: Python :: 3
Classifier: Programming Language :: Python :: 3.8
Classifier: Programming Language :: Python :: 3.9
Classifier: Programming Language :: Python :: 3.10
Classifier: Programming Language :: Python :: 3.11
Classifier: Programming Language :: Python :: 3.12
Classifier: Operating System :: OS Independent
Classifier: Topic :: Software Development :: Libraries :: Python Modules
Classifier: Topic :: Utilities
Classifier: Topic :: Security
Classifier: Topic :: Scientific/Engineering :: Electronic Design Automation (EDA)
Classifier: Environment :: X11 Applications :: Qt
Classifier: Typing :: Typed
Requires-Python: >=3.8
License-File: LICENSE
Requires-Dist: pyside6
Requires-Dist: pyyaml
Requires-Dist: tomli-w
Requires-Dist: jinja2
Provides-Extra: dev
Requires-Dist: flake8 ; extra == 'dev'
Requires-Dist: pep8-naming ; extra == 'dev'
Requires-Dist: mypy ; extra == 'dev'
Requires-Dist: types-PyYAML ; extra == 'dev'
Requires-Dist: tox ; extra == 'dev'
Requires-Dist: pytest ; extra == 'dev'
Requires-Dist: setuptools ; extra == 'dev'
Requires-Dist: sphinx ; extra == 'dev'
Requires-Dist: sphinx-rtd-theme ; extra == 'dev'
Provides-Extra: docs
Requires-Dist: sphinx ; extra == 'docs'
Requires-Dist: sphinx-rtd-theme ; extra == 'docs'
